flap/__init__.py
flap/engine.py
flap/ui.py
flap/latex/__init__.py
flap/latex/commons.py
flap/latex/errors.py
flap/latex/lexer.py
flap/latex/parser.py
flap/latex/symbols.py
flap/latex/tokens.py
flap/latex/macros/__init__.py
flap/latex/macros/biblatex.py
flap/latex/macros/bibliography.py
flap/latex/macros/commons.py
flap/latex/macros/core.py
flap/latex/macros/factory.py
flap/latex/macros/graphics.py
flap/latex/macros/inlining.py
flap/latex/macros/listings.py
flap/util/__init__.py
flap/util/oofs.py
flap/util/path.py
tests/__init__.py
tests/commons.py
tests/latex_project.py
tests/test_latex_project.py
tests/acceptance/__init__.py
tests/acceptance/misc.py
tests/acceptance/test_yaml.py
tests/acceptance/yaml.py
tests/unit/__init__.py
tests/unit/latex/__init__.py
tests/unit/latex/test_classification.py
tests/unit/latex/test_commons.py
tests/unit/latex/test_evaluation.py
tests/unit/latex/test_lexer.py
tests/unit/latex/test_macro.py
tests/unit/latex/test_parser.py
tests/unit/latex/test_tokens.py
tests/unit/util/__init__.py
tests/unit/util/test_oofs.py
tests/unit/util/test_path.py
FLaP-0.6.0.dist-info/LICENSE.txt
FLaP-0.6.0.dist-info/METADATA
FLaP-0.6.0.dist-info/WHEEL
FLaP-0.6.0.dist-info/entry_points.txt
FLaP-0.6.0.dist-info/top_level.txt
FLaP-0.6.0.dist-info/RECORD
