Metadata-Version: 2.1
Name: FLaP
Version: 0.6.0
Summary: Flat LaTeX Projects
Home-page: https://github.com/fchauvel/flap
Author: Franck Chauvel
Author-email: franck.chauvel@gmail.com
License: GPLv3
Download-URL: https://github.com/fchauvel/flap/tarball/v0.6.0
Platform: UNKNOWN
Classifier: Development Status :: 4 - Beta
Classifier: Intended Audience :: Science/Research
Classifier: Environment :: Console
Classifier: License :: OSI Approved :: GNU General Public License v3 or later (GPLv3+)
Classifier: Natural Language :: English
Classifier: Topic :: Text Processing :: Markup :: LaTeX
Classifier: Programming Language :: Python :: 3.3
Classifier: Programming Language :: Python :: 3.4
Classifier: Programming Language :: Python :: 3.5
Classifier: Programming Language :: Python :: 3.6
Requires-Dist: PyYAML (==5.4.1)
Requires-Dist: click (==7.1.2)
Requires-Dist: enum34 (==1.1.10)
Provides-Extra: test
Requires-Dist: pytest (==6.2.2) ; extra == 'test'
Requires-Dist: coverage (==5.5) ; extra == 'test'
Requires-Dist: mock (==4.0.3) ; extra == 'test'
Requires-Dist: wheel (==0.36.2) ; extra == 'test'
Requires-Dist: twine (==3.3.0) ; extra == 'test'
